LICENSE
MANIFEST.in
README.rst
requirements.txt
setup.cfg
setup.py
kiss2/__init__.py
kiss2/classes.py
kiss2/constants.py
kiss2/exceptions.py
kiss2/util.py
kiss2.egg-info/PKG-INFO
kiss2.egg-info/SOURCES.txt
kiss2.egg-info/dependency_links.txt
kiss2.egg-info/not-zip-safe
kiss2.egg-info/requires.txt
kiss2.egg-info/top_level.txt