Metadata-Version: 1.1
Name: kiss2
Version: 7.0.1
Summary: Python KISS Module V2.
Home-page: https://git.scd31.com/laptopdude90/kiss2
Author: Stephen Downward
Author-email: stephen@stephendownward.ca
License: Copyright 2017 Greg Albrecht and Contributors
